quantlyx/__init__.py
quantlyx/command.py
quantlyx-0.0.1.dist-info/LICENSE
quantlyx-0.0.1.dist-info/METADATA
quantlyx-0.0.1.dist-info/WHEEL
quantlyx-0.0.1.dist-info/entry_points.txt
quantlyx-0.0.1.dist-info/top_level.txt
quantlyx-0.0.1.dist-info/RECORD
