Metadata-Version: 2.1
Name: quantlyx
Version: 0.0.1
Summary: QuantlyX
Author: liangyongxiong
Author-email: me@liangyongxiong.cn
License: MIT
Keywords: quantlyx
Classifier: Development Status :: 1 - Planning
Classifier: Environment :: Console
Classifier: Intended Audience :: Developers
Classifier: License :: Free for non-commercial use
Classifier: Programming Language :: Python :: 3
Classifier: Topic :: Office/Business
Classifier: Topic :: Office/Business :: Financial
Classifier: Topic :: Software Development
Classifier: Topic :: Software Development :: Libraries
Classifier: Topic :: Software Development :: Libraries :: Python Modules
Requires-Python: >=3.7
License-File: LICENSE
Requires-Dist: requests
Requires-Dist: attrdict
Requires-Dist: tqdm
